print_links.py
print_links-0.3.dist-info/METADATA
print_links-0.3.dist-info/WHEEL
print_links-0.3.dist-info/entry_points.txt
print_links-0.3.dist-info/licenses/LICENSE
print_links-0.3.dist-info/RECORD
